church_of_jesus_christ_api/README
church_of_jesus_christ_api/__init__.py
church_of_jesus_christ_api/__version__.py
church_of_jesus_christ_api/church_of_jesus_christ_api.py
church_of_jesus_christ_api-0.4.0.dist-info/METADATA
church_of_jesus_christ_api-0.4.0.dist-info/WHEEL
church_of_jesus_christ_api-0.4.0.dist-info/top_level.txt
church_of_jesus_christ_api-0.4.0.dist-info/RECORD
