Metadata-Version: 2.4
Name: church_of_jesus_christ_api
Version: 0.4.0
Summary: Decommisioned package
Home-page: https://github.com/mackliet/church_of_jesus_christ_api
Author: Michael Mackliet
Author-email: michael@mackliet.com
Dynamic: author
Dynamic: author-email
Dynamic: description
Dynamic: description-content-type
Dynamic: home-page
Dynamic: summary
